eso/__init__.py
eso/_version.py
eso/eso.py
eso/ga/__init__.py
eso/ga/chromosome.py
eso/ga/gene.py
eso/ga/operator.py
eso/ga/population.py
eso/ga/selection.py
eso/model/__init__.py
eso/model/cnn.py
eso/model/data.py
eso/model/model.py
eso/utils/AnnotationReader.py
eso/utils/Evaluation.py
eso/utils/__init__.py
eso/utils/_settings_types.py
eso/utils/logger.py
eso/utils/preprocessing.py
eso/utils/settings.py
eso/utils/test_settings.py
eso/utils/unpickler.py
eso-0.1.0.dev68.dist-info/licenses/COPYING.md
eso-0.1.0.dev68.dist-info/licenses/LICENSE.md
eso-0.1.0.dev68.dist-info/METADATA
eso-0.1.0.dev68.dist-info/WHEEL
eso-0.1.0.dev68.dist-info/top_level.txt
eso-0.1.0.dev68.dist-info/RECORD
