Metadata-Version: 2.4
Name: eso
Version: 0.1.0.dev68
Summary: Evolutionary Spectrogram Optimisation : optimise the selection and size of frequency bands of spectrograms to maximise deep learning classification accuracy while minimising the model's size using genetic algorithms
Maintainer-email: Ufuk Çakır <your@email.com>
License: MIT
Classifier: Programming Language :: Python :: 3
Classifier: Operating System :: OS Independent
Classifier: License :: OSI Approved :: MIT License
Requires-Python: <3.13,>=3.10
License-File: LICENSE.md
License-File: COPYING.md
Requires-Dist: librosa==0.10.1
Requires-Dist: matplotlib>=3.10.1
Requires-Dist: numpy>=2.2.5
Requires-Dist: opencv-python-headless>=4.8.1.78
Requires-Dist: pandas>=2.2.3
Requires-Dist: pre-commit>=4.2.0
Requires-Dist: pyqt5>=5.15.11
Requires-Dist: pytest-cov>=5.0.0
Requires-Dist: pytest-mock>=3.14.0
Requires-Dist: scikit-learn>=1.6.1
Requires-Dist: setuptools>=79.0.0
Requires-Dist: sympy>=1.14.0
Requires-Dist: resampy>=0.4.3
Requires-Dist: tensorboard>=2.19.0
Requires-Dist: torch>=2.8.0
Requires-Dist: tqdm>=4.67.1
Requires-Dist: yattag>=1.16.1
Provides-Extra: tests
Requires-Dist: pytest; extra == "tests"
Requires-Dist: pytest-cov; extra == "tests"
Requires-Dist: nbval; extra == "tests"
Provides-Extra: docs
Requires-Dist: ipykernel; extra == "docs"
Requires-Dist: nbsphinx; extra == "docs"
Requires-Dist: nbsphinx-link; extra == "docs"
Requires-Dist: sphinx; extra == "docs"
Requires-Dist: sphinx_mdinclude; extra == "docs"
Requires-Dist: sphinx_rtd_theme; extra == "docs"
Requires-Dist: pydata-sphinx-theme; extra == "docs"
Dynamic: license-file
